adder.v
// Adder circuit

`define AND and #50
`define OR or #50
`define NOT not #50
`define XOR xor #50

module behavioralFullAdder
(
    output sum, 
    output carryout,
    input a, 
    input b, 
    input carryin
);
    // Uses concatenation operator and built-in '+'
    assign {carryout, sum}=a+b+carryin;
endmodule

module structuralFullAdder
(
    output sum, 
    output carryout,
    input A, 
    input B, 
    input carryin
);
    wire AxorB;
    wire AxorBandC;
    wire AandB;

    `XOR AxorBgate(AxorB, A, B);
    `XOR AxorBxorCgate(sum, AxorB, carryin);
    `AND AandBgate(AandB,A,B);
    `AND AxorBandCgate(AxorBandC, AxorB, carryin);
    `OR  orgate(carryout, AxorBandC, AandB);

endmodule

adder.t.v
// Adder testbench
`timescale 1 ns / 1 ps
`include "adder.v"
`define DELAY 500

module testFullAdder();
    reg a, b, carryin;
    wire sum, carryout;
    wire my_sum, my_carryout;

    behavioralFullAdder adder (sum, carryout, a, b, carryin);
    structuralFullAdder my_adder (my_sum, my_carryout, a, b, carryin);

    initial begin
    	$dumpfile("adder.vcd");
    	$dumpvars();
        $display("One Bit Full Adder");
	    $display("A  B Cin | Cout Sum | BenCout BenSum | MyCout MySum");            // Prints header for truth table
	    a=0;b=0;carryin = 0; #`DELAY                                 // Set A and B, wait for update (#1)
	    $display("%b  %b  %b  |  0    0  |    %b      %b    |    %b     %b  ", a, b, carryin, carryout, sum, my_carryout, my_sum);
	    a=0;b=0;carryin = 1; #`DELAY                                 // Set A and B, wait for update (#1)
	    $display("%b  %b  %b  |  0    1  |    %b      %b    |    %b     %b  ", a, b, carryin, carryout, sum, my_carryout, my_sum);
	    a=0;b=1;carryin = 0; #`DELAY                                 // Set A and B, wait for update (#1)
	    $display("%b  %b  %b  |  0    1  |    %b      %b    |    %b     %b  ", a, b, carryin, carryout, sum, my_carryout, my_sum);
	    a=0;b=1;carryin = 1; #`DELAY                                 // Set A and B, wait for update (#1)
	    $display("%b  %b  %b  |  1    0  |    %b      %b    |    %b     %b  ", a, b, carryin, carryout, sum, my_carryout, my_sum);
	    a=1;b=0;carryin = 0; #`DELAY                                 // Set A and B, wait for update (#1)
	    $display("%b  %b  %b  |  0    1  |    %b      %b    |    %b     %b  ", a, b, carryin, carryout, sum, my_carryout, my_sum);
	    a=1;b=0;carryin = 1; #`DELAY                                 // Set A and B, wait for update (#1)
	    $display("%b  %b  %b  |  1    0  |    %b      %b    |    %b     %b  ", a, b, carryin, carryout, sum, my_carryout, my_sum);
	    a=1;b=1;carryin = 0; #`DELAY                                 // Set A and B, wait for update (#1)
	    $display("%b  %b  %b  |  1    0  |    %b      %b    |    %b     %b  ", a, b, carryin, carryout, sum, my_carryout, my_sum);
	    a=1;b=1;carryin = 1; #`DELAY                                 // Set A and B, wait for update (#1)
	    $display("%b  %b  %b  |  1    1  |    %b      %b    |    %b     %b  ", a, b, carryin, carryout, sum, my_carryout, my_sum);
	    
	    
    end
endmodule

adder.vcd
$date
	Thu Sep 20 18:20:51 2018
$end
$version
	Icarus Verilog
$end
$timescale
	1ps
$end
$scope module testFullAdder $end
$var wire 1 ! sum $end
$var wire 1 " my_sum $end
$var wire 1 # my_carryout $end
$var wire 1 $ carryout $end
$var reg 1 % a $end
$var reg 1 & b $end
$var reg 1 ' carryin $end
$scope module adder $end
$var wire 1 % a $end
$var wire 1 & b $end
$var wire 1 ' carryin $end
$var wire 1 ! sum $end
$var wire 1 $ carryout $end
$upscope $end
$scope module my_adder $end
$var wire 1 % A $end
$var wire 1 ( AandB $end
$var wire 1 ) AxorB $end
$var wire 1 * AxorBandC $end
$var wire 1 & B $end
$var wire 1 ' carryin $end
$var wire 1 # carryout $end
$var wire 1 " sum $end
$upscope $end
$upscope $end
$enddefinitions $end
#0
$dumpvars
x*
x)
x(
0'
0&
0%
0$
x#
x"
0!
$end
#50000
0*
0(
0)
#100000
0#
0"
#500000
1!
1'
#550000
1"
#1000000
0'
1&
#1050000
0"
1)
#1100000
1"
#1500000
0!
1$
1'
#1550000
0"
1*
#1600000
1#
#2000000
0$
1!
0'
0&
1%
#2050000
1"
0*
#2100000
0#
#2500000
0!
1$
1'
#2550000
0"
1*
#2600000
1#
#3000000
0'
1&
#3050000
1"
0*
0)
1(
#3100000
0"
#3500000
1!
1'
#3550000
1"
