decoder.v
// Decoder circuit
`define AND and #50
`define OR or #50
`define NOT not #50

module behavioralDecoder
(
    output out0, out1, out2, out3,
    input address0, address1,
    input enable
);
    // Uses concatenation and shift operators
    assign {out3,out2,out1,out0}=enable<<{address1,address0};
endmodule


module structuralDecoder
(
    output out0, out1, out2, out3,
    input A, B, //A = address0, B = address1
    input enable
);
    wire nA;
    wire nB;
    wire and0;
    wire and1;
    wire and2;
    wire and3;

    `NOT Ainv(nA, A);
    `NOT Binv(nB, B);
    `AND and1gate(and0, nA, nB);
    `AND and2gate(and1, A, nB);
    `AND and3gate(and2, nA, B);
    `AND and4gate(and3, A, B);
    `AND out1gate(out0, and0, enable);
    `AND out2gate(out1, and1, enable);
    `AND out3gate(out2, and2, enable);
    `AND out4gate(out3, and3, enable);
endmodule

decoder.t.v
// Decoder testbench
`timescale 1 ns / 1 ps
`include "decoder.v"

module testDecoder (); 
    reg addr0, addr1;
    reg enable;
    wire out0,out1,out2,out3;
    wire myout0, myout1, myout2, myout3;

    behavioralDecoder decoder (out0,out1,out2,out3,addr0,addr1,enable);
    structuralDecoder my_decoder (myout0,myout1,myout2,myout3,addr0,addr1,enable); // Swap after testing

    initial begin
    $dumpfile("decoder.vcd");
    $dumpvars();
    $display(" Inputs | Ben Outputs | My Outputs  | ");
    $display("En A0 A1| O0 O1 O2 O3 | O0 O1 O2 O3 | Expected Output");
    enable=0;addr0=0;addr1=0; #500 
    $display("%b  %b  %b |  %b  %b  %b  %b |  %b  %b  %b  %b | All false", enable, addr0, addr1, out0, out1, out2, out3,myout0, myout1, myout2, myout3);
    enable=0;addr0=1;addr1=0; #500
    $display("%b  %b  %b |  %b  %b  %b  %b |  %b  %b  %b  %b | All false", enable, addr0, addr1, out0, out1, out2, out3,myout0, myout1, myout2, myout3);
    enable=0;addr0=0;addr1=1; #500 
    $display("%b  %b  %b |  %b  %b  %b  %b |  %b  %b  %b  %b | All false", enable, addr0, addr1, out0, out1, out2, out3,myout0, myout1, myout2, myout3);
    enable=0;addr0=1;addr1=1; #500 
    $display("%b  %b  %b |  %b  %b  %b  %b |  %b  %b  %b  %b | All false", enable, addr0, addr1, out0, out1, out2, out3,myout0, myout1, myout2, myout3);
    enable=1;addr0=0;addr1=0; #500 
    $display("%b  %b  %b |  %b  %b  %b  %b |  %b  %b  %b  %b | O0 Only", enable, addr0, addr1, out0, out1, out2, out3,myout0, myout1, myout2, myout3);
    enable=1;addr0=1;addr1=0; #500 
    $display("%b  %b  %b |  %b  %b  %b  %b |  %b  %b  %b  %b | O1 Only", enable, addr0, addr1, out0, out1, out2, out3,myout0, myout1, myout2, myout3);
    enable=1;addr0=0;addr1=1; #500 
    $display("%b  %b  %b |  %b  %b  %b  %b |  %b  %b  %b  %b | O2 Only", enable, addr0, addr1, out0, out1, out2, out3,myout0, myout1, myout2, myout3);
    enable=1;addr0=1;addr1=1; #500 
    $display("%b  %b  %b |  %b  %b  %b  %b |  %b  %b  %b  %b | O3 Only", enable, addr0, addr1, out0, out1, out2, out3,myout0, myout1, myout2, myout3);
    end

endmodule

decoder.vcd
$date
	Thu Sep 20 18:18:11 2018
$end
$version
	Icarus Verilog
$end
$timescale
	1ps
$end
$scope module testDecoder $end
$var wire 1 ! out3 $end
$var wire 1 " out2 $end
$var wire 1 # out1 $end
$var wire 1 $ out0 $end
$var wire 1 % myout3 $end
$var wire 1 & myout2 $end
$var wire 1 ' myout1 $end
$var wire 1 ( myout0 $end
$var reg 1 ) addr0 $end
$var reg 1 * addr1 $end
$var reg 1 + enable $end
$scope module decoder $end
$var wire 1 ) address0 $end
$var wire 1 * address1 $end
$var wire 1 + enable $end
$var wire 1 ! out3 $end
$var wire 1 " out2 $end
$var wire 1 # out1 $end
$var wire 1 $ out0 $end
$upscope $end
$scope module my_decoder $end
$var wire 1 ) A $end
$var wire 1 * B $end
$var wire 1 , and0 $end
$var wire 1 - and1 $end
$var wire 1 . and2 $end
$var wire 1 / and3 $end
$var wire 1 + enable $end
$var wire 1 0 nA $end
$var wire 1 1 nB $end
$var wire 1 ( out0 $end
$var wire 1 ' out1 $end
$var wire 1 & out2 $end
$var wire 1 % out3 $end
$upscope $end
$upscope $end
$enddefinitions $end
#0
$dumpvars
x1
x0
x/
x.
x-
x,
0+
0*
0)
x(
x'
x&
x%
0$
0#
0"
0!
$end
#50000
11
10
0%
0&
0'
0(
0/
0.
0-
#100000
1,
#500000
1)
#550000
00
1-
#600000
0,
#1000000
1*
0)
#1050000
01
10
0-
#1100000
1.
#1500000
1)
#1550000
00
1/
#1600000
0.
#2000000
1$
0*
0)
1+
#2050000
11
10
0/
1%
#2100000
1,
0%
#2150000
1(
#2500000
0$
1#
1)
#2550000
00
1-
#2600000
0,
1'
#2650000
0(
#3000000
1"
0#
1*
0)
#3050000
01
10
0-
#3100000
1.
0'
#3150000
1&
#3500000
0"
1!
1)
#3550000
00
1/
#3600000
0.
1%
#3650000
0&
